alesha/alesha.py
alesha/ryabov.py
alesha/test_2.py
alesha-2.1.1.dist-info/METADATA
alesha-2.1.1.dist-info/WHEEL
alesha-2.1.1.dist-info/RECORD
